<?xml version="1.0" encoding="UTF-8" ?>
<ufoanalyzer_record version ="200"
	 clip_name="M20090925_211240_Shigaraki_MU" o="1" y="2009" mo="9"
	 d="25" h="21" m="12" s="40.000000"
	 tz="32400" tme="1.000000" lid="Shigaraki" sid="200F1.8"
	 lng="136.104370" lat="34.853970" alt="390.000000" cx="720"
	 cy="480" fps="29.970089" interlaced="1" bbf="0"
	 frames="68" head="30" tail="0" drop="0"
	 dlev="0" dsize="0" sipos="0" sisize="0"
	 trig="0" observer="Kero&Szasz" cam="Hamamatsu_ICCD" lens="Canon200mmF1.8"
	 cap="" u2="" ua="244" memo=""
	 az="71.206924" ev="89.824699" rot="-108.973206" vx="4.312501"
	 yx="1.102954" dx="-216.955338" dy="-99.652649" k4="0.000000"
	 k3="0.003433" k2="-0.005805" atc="58.299999" BVF="-0.300000"
	 maxLev="255" maxMag="8.372000" minLev="47" mimMag="10.200000"
	 dl="19" leap="40" pixs="44" rstar="61"
	 ddega="0.003914" ddegm="0.008501" errm="0.196625" Lmrgn="5"
	 Rmrgn="5" Dmrgn="5" Umrgn="5">
	<ua2_objects>
<ua2_object
	 fs="60" fe="74" fN="15" sN="9"
	 sec="0.233567" av="6.021363" pix="38" bmax="38"
	 bN="0" Lmax="391.428558" mag="7.906719" cdeg="0.001185"
	 cdegmax="0.002674" io="3" raP="126.959206" dcP="53.792404"
	 av1="6.021363" x1="23.685781" y1="147.124115" x2="71.961014"
	 y2="154.552475" az1="83.341331" ev1="89.180595" az2="75.739182"
	 ev2="89.430611" azm="70.415504" evm="89.527229" ra1="324.606842"
	 dc1="34.900757" ra2="324.287750" dc2="34.948357" ram="324.158051"
	 dcm="34.967285" class="spo" m="0" dr="-1.000000"
	 dv="-1.000000" Vo="-1.000000" lng1="136.119644" lat1="34.855431"
	 h1="100.000000" dist1="99.620033" gd1="1.402719" azL1="-1.000000"
	 evL1="-1.000000" lng2="-999.000000" lat2="-999.000000" h2="-1.000000"
	 dist2="-1.000000" gd2="-1.000000" len="0.000000" GV="0.000000"
	 rao="-1.000000" dco="-1.000000" Voo="-1.000000" rat="0.000000"
	 dct="0.000000" memo="">
	<ua2_objpath>
<ua2_fdata2 fno=" 60" b=" 36" bm="000" Lsum="   195.2" mag="+8.66" az="  83.3413283" ev="  89.1805918" ra=" 324.6068314" dec=" +34.9007577"></ua2_fdata2>
<ua2_fdata2 fno=" 61" b=" 37" bm="000" Lsum="   391.4" mag="+7.91" az="  84.6423433" ev="  89.1110284" ra=" 324.6934805" dec=" +34.8879665"></ua2_fdata2>
<ua2_fdata2 fno=" 63" b=" 34" bm="000" Lsum="   153.7" mag="+8.92" az="  80.9777844" ev="  89.2772039" ra=" 324.4850829" dec=" +34.9200868"></ua2_fdata2>
<ua2_fdata2 fno=" 64" b=" 36" bm="000" Lsum="   162.3" mag="+8.86" az="  69.9939162" ev="  89.5310027" ra=" 324.1522981" dec=" +34.9692963"></ua2_fdata2>
<ua2_fdata2 fno=" 65" b=" 34" bm="000" Lsum="   158.6" mag="+8.89" az="  73.7638179" ev="  89.4726414" ra=" 324.2322766" dec=" +34.9558684"></ua2_fdata2>
<ua2_fdata2 fno=" 67" b=" 33" bm="000" Lsum="    76.1" mag="+9.68" az="  57.6567177" ev="  89.6572263" ra=" 323.9680265" dec=" +34.9929985"></ua2_fdata2>
<ua2_fdata2 fno=" 68" b=" 36" bm="000" Lsum="   122.0" mag="+9.17" az="  12.9235270" ev="  89.7664697" ra=" 323.6783528" dec=" +35.0378891"></ua2_fdata2>
<ua2_fdata2 fno=" 69" b=" 32" bm="000" Lsum="   140.1" mag="+9.02" az="  32.7871363" ev="  89.7499065" ra=" 323.7799198" dec=" +35.0203729"></ua2_fdata2>
<ua2_fdata2 fno=" 74" b=" 38" bm="000" Lsum="   128.0" mag="+9.12" az=" 302.0603497" ev="  89.3847230" ra=" 322.9770253" dec=" +35.1356196"></ua2_fdata2>
	</ua2_objpath>
</ua2_object>
	</ua2_objects>
</ufoanalyzer_record>
