<?xml version="1.0" encoding="UTF-8" ?>
<ufoanalyzer_record version ="200"
	 clip_name="M20091214_012454_Shigaraki_MU" o="1" y="2009" mo="12"
	 d="14" h="1" m="24" s="54.000000"
	 tz="32400" tme="1.000000" lid="Shigaraki" sid="200F1.8"
	 lng="136.104370" lat="34.853970" alt="390.000000" cx="720"
	 cy="480" fps="29.970089" interlaced="1" bbf="0"
	 frames="67" head="30" tail="0" drop="0"
	 dlev="0" dsize="0" sipos="0" sisize="0"
	 trig="0" observer="Kero&Szasz" cam="Hamamatsu_ICCD" lens="Canon200mmF1.8"
	 cap="" u2="" ua="244" memo=""
	 az="88.161827" ev="86.885979" rot="-94.929359" vx="9.894052"
	 yx="1.104767" dx="-232.584122" dy="42.090084" k4="0.000000"
	 k3="0.002272" k2="-0.006017" atc="58.299999" BVF="-0.300000"
	 maxLev="255" maxMag="7.278000" minLev="17" mimMag="10.200000"
	 dl="21" leap="40" pixs="64" rstar="183"
	 ddega="0.008078" ddegm="0.042665" errm="0.293568" Lmrgn="5"
	 Rmrgn="5" Dmrgn="5" Umrgn="5">
	<ua2_objects>
<ua2_object
	 fs="61" fe="73" fN="13" sN="11"
	 sec="0.200200" av="3.770633" pix="51" bmax="52"
	 bN="0" Lmax="474.000000" mag="6.604905" cdeg="0.003270"
	 cdegmax="0.007275" io="3" raP="99.311913" dcP="-56.703739"
	 av1="3.386299" x1="634.860168" y1="139.736374" x2="662.730652"
	 y2="139.712891" az1="245.380341" ev1="86.371185" az2="247.723785"
	 ev2="86.060829" azm="247.594849" evm="86.079453" ra1="100.704178"
	 dc1="33.288498" ra2="100.289452" dc2="33.292431" ram="100.314110"
	 dcm="33.292236" class="J5_Gem" m="0" dr="0.335093"
	 dv="-13.127903" Vo="30.666107" lng1="136.045288" lat1="34.831730"
	 h1="95.333511" dist1="95.131447" gd1="5.932698" azL1="287.910645"
	 evL1="82.302528" lng2="136.041367" lat2="34.832771" h2="91.934807"
	 dist2="92.144585" gd2="6.214143" len="3.419432" GV="17.080061"
	 rao="-1.000000" dco="-1.000000" Voo="-1.000000" rat="0.000000"
	 dct="0.000000" memo="">
	<ua2_objpath>
<ua2_fdata2 fno=" 61" b=" 43" bm="000" Lsum="   138.6" mag="+7.94" az=" 244.5118930" ev="  86.4879549" ra=" 100.8579850" dec=" +33.2939643"></ua2_fdata2>
<ua2_fdata2 fno=" 62" b=" 41" bm="000" Lsum="    95.6" mag="+8.34" az=" 245.9883875" ev="  86.2880110" ra=" 100.5943621" dec=" +33.2860233"></ua2_fdata2>
<ua2_fdata2 fno=" 63" b=" 43" bm="000" Lsum="   221.4" mag="+7.43" az=" 245.3181137" ev="  86.3834123" ra=" 100.7193489" dec=" +33.2905271"></ua2_fdata2>
<ua2_fdata2 fno=" 64" b=" 43" bm="000" Lsum="   289.1" mag="+7.14" az=" 246.8222247" ev="  86.1758882" ra=" 100.4450762" dec=" +33.2861799"></ua2_fdata2>
<ua2_fdata2 fno=" 65" b=" 45" bm="000" Lsum="   159.1" mag="+7.79" az=" 246.2230786" ev="  86.2715291" ra=" 100.5686224" dec=" +33.2923949"></ua2_fdata2>
<ua2_fdata2 fno=" 67" b=" 45" bm="000" Lsum="   154.8" mag="+7.82" az=" 247.2842447" ev="  86.1246993" ra=" 100.3738431" dec=" +33.2922565"></ua2_fdata2>
<ua2_fdata2 fno=" 68" b=" 45" bm="000" Lsum="   403.0" mag="+6.78" az=" 248.5575820" ev="  85.9369373" ra=" 100.1257187" dec=" +33.2941999"></ua2_fdata2>
<ua2_fdata2 fno=" 69" b=" 52" bm="000" Lsum="   474.0" mag="+6.60" az=" 248.2081994" ev="  85.9968024" ra=" 100.2030973" dec=" +33.2963223"></ua2_fdata2>
<ua2_fdata2 fno=" 70" b=" 40" bm="000" Lsum="   166.5" mag="+7.74" az=" 249.4482488" ev="  85.7809500" ra="  99.9239169" dec=" +33.2905282"></ua2_fdata2>
<ua2_fdata2 fno=" 71" b=" 46" bm="000" Lsum="   384.2" mag="+6.83" az=" 248.9837813" ev="  85.8773136" ra=" 100.0457614" dec=" +33.2979097"></ua2_fdata2>
<ua2_fdata2 fno=" 73" b=" 40" bm="000" Lsum="    90.3" mag="+8.41" az=" 249.7539089" ev="  85.7471944" ra="  99.8761694" dec=" +33.2980330"></ua2_fdata2>
	</ua2_objpath>
</ua2_object>
	</ua2_objects>
</ufoanalyzer_record>
