<?xml version="1.0" encoding="UTF-8" ?>
<ufoanalyzer_record version ="200"
	 clip_name="M20091214_004455_Shigaraki_MU" o="1" y="2009" mo="12"
	 d="14" h="0" m="44" s="55.000000"
	 tz="32400" tme="1.000000" lid="Shigaraki" sid="200F1.8"
	 lng="136.104370" lat="34.853970" alt="390.000000" cx="720"
	 cy="480" fps="29.970089" interlaced="1" bbf="0"
	 frames="91" head="30" tail="0" drop="0"
	 dlev="0" dsize="0" sipos="0" sisize="0"
	 trig="0" observer="Kero&Szasz" cam="Hamamatsu_ICCD" lens="Canon200mmF1.8"
	 cap="" u2="" ua="244" memo=""
	 az="88.158005" ev="86.889236" rot="-94.916298" vx="9.894052"
	 yx="1.104767" dx="-232.584122" dy="42.090084" k4="0.000000"
	 k3="0.002272" k2="-0.006017" atc="58.299999" BVF="-0.300000"
	 maxLev="255" maxMag="7.491000" minLev="21" mimMag="10.200000"
	 dl="22" leap="40" pixs="1405" rstar="149"
	 ddega="0.006080" ddegm="0.019720" errm="0.210884" Lmrgn="5"
	 Rmrgn="5" Dmrgn="5" Umrgn="5">
	<ua2_objects>
<ua2_object
	 fs="110" fe="115" fN="6" sN="4"
	 sec="0.083416" av="16.904287" pix="920" bmax="255"
	 bN="34" Lmax="78978.289063" mag="1.263581" cdeg="0.000424"
	 cdegmax="0.000449" io="3" raP="308.461884" dcP="53.202343"
	 av1="17.080290" x1="266.733215" y1="80.702316" x2="322.932770"
	 y2="59.610176" az1="154.415878" ev1="87.151817" az2="169.647018"
	 ev2="87.132202" azm="164.870178" evm="87.159698" ra1="96.082687"
	 dc1="32.282261" ra2="95.236366" dc2="32.036469" ram="95.503479"
	 dcm="32.114349" class="spo" m="0" dr="-1.000000"
	 dv="-1.000000" Vo="-1.000000" lng1="136.127441" lat1="34.814392"
	 h1="100.000000" dist1="99.731300" gd1="4.879337" azL1="-1.000000"
	 evL1="-1.000000" lng2="-999.000000" lat2="-999.000000" h2="-1.000000"
	 dist2="-1.000000" gd2="-1.000000" len="0.000000" GV="0.000000"
	 rao="53.874763" dco="11.244165" Voo="43.430000" rat="52.865589"
	 dct="10.680282" memo="">
	<ua2_objpath>
<ua2_fdata2 fno="110" b="255" bm="018" Lsum=" 34482.6" mag="+2.16" az=" 154.4158715" ev="  87.1518158" ra="  96.0826890" dec=" +32.2822612"></ua2_fdata2>
<ua2_fdata2 fno="112" b="255" bm="015" Lsum=" 57082.6" mag="+1.62" az=" 164.8694993" ev="  87.1592488" ra="  95.5036526" dec=" +32.1139243"></ua2_fdata2>
<ua2_fdata2 fno="113" b="255" bm="034" Lsum=" 78978.3" mag="+1.26" az=" 158.7776580" ev="  87.1659580" ra="  95.8405171" dec=" +32.2117741"></ua2_fdata2>
<ua2_fdata2 fno="115" b="251" bm="000" Lsum=" 13613.4" mag="+3.17" az=" 169.6470139" ev="  87.1322009" ra="  95.2363686" dec=" +32.0364676"></ua2_fdata2>
	</ua2_objpath>
</ua2_object>
	</ua2_objects>
</ufoanalyzer_record>
