<?xml version="1.0" encoding="UTF-8" ?>
<ufoanalyzer_record version ="200"
	 clip_name="M20101215_003615_Shigaraki_MU" o="1" y="2010" mo="12"
	 d="15" h="0" m="36" s="15.000000"
	 tz="32400" tme="1.000000" lid="Shigaraki" sid="200F1.8"
	 lng="136.104370" lat="34.853970" alt="390.000000" cx="720"
	 cy="480" fps="29.970089" interlaced="1" bbf="0"
	 frames="113" head="30" tail="0" drop="0"
	 dlev="0" dsize="0" sipos="0" sisize="0"
	 trig="0" observer="Kero&Szasz" cam="Hamamatsu_ICCD" lens="Canon200mmF1.8"
	 cap="" u2="" ua="244" memo=""
	 az="223.963837" ev="89.444153" rot="44.002144" vx="9.884752"
	 yx="1.104551" dx="28.859592" dy="13.790000" k4="0.000000"
	 k3="0.007687" k2="-0.008759" atc="58.299999" BVF="-0.300000"
	 maxLev="255" maxMag="6.311000" minLev="7" mimMag="10.200000"
	 dl="21" leap="40" pixs="230" rstar="145"
	 ddega="0.014647" ddegm="0.038857" errm="0.609359" Lmrgn="5"
	 Rmrgn="5" Dmrgn="5" Umrgn="5">
	<ua2_objects>
<ua2_object
	 fs="62" fe="77" fN="16" sN="16"
	 sec="0.250250" av="10.885088" pix="224" bmax="46"
	 bN="0" Lmax="1219.142822" mag="4.612214" cdeg="0.002490"
	 cdegmax="0.007335" io="3" raP="20.231449" dcP="-16.328863"
	 av1="10.448028" x1="93.859459" y1="469.819855" x2="14.267256"
	 y2="300.205811" az1="51.927002" ev1="85.832603" az2="86.767853"
	 ev2="85.721008" azm="68.138329" evm="85.973999" ra1="97.305664"
	 dc1="37.362740" ra2="98.399200" dc2="34.992882" ram="97.815819"
	 dcm="36.274059" class="spo" m="0" dr="-1.000000"
	 dv="-1.000000" Vo="-1.000000" lng1="136.166046" lat1="34.893581"
	 h1="100.000000" dist1="99.869987" gd1="7.145905" azL1="-1.000000"
	 evL1="-1.000000" lng2="-999.000000" lat2="-999.000000" h2="-1.000000"
	 dist2="-1.000000" gd2="-1.000000" len="0.000000" GV="0.000000"
	 rao="80.809715" dco="59.188553" Voo="43.660000" rat="79.473976"
	 dct="59.490040" memo="">
	<ua2_objpath>
<ua2_fdata2 fno=" 62" b=" 40" bm="000" Lsum="   747.4" mag="+5.14" az="  53.8273257" ev="  85.8596162" ra="  97.3763878" dec=" +37.2342473"></ua2_fdata2>
<ua2_fdata2 fno=" 63" b=" 36" bm="000" Lsum="    81.9" mag="+7.54" az="  52.6963839" ev="  85.8395933" ra="  97.3391179" dec=" +37.3131192"></ua2_fdata2>
<ua2_fdata2 fno=" 64" b=" 46" bm="000" Lsum="  1144.1" mag="+4.68" az="  58.6177671" ev="  85.9335688" ra="  97.5207136" dec=" +36.9031375"></ua2_fdata2>
<ua2_fdata2 fno=" 65" b=" 40" bm="000" Lsum="   782.4" mag="+5.09" az="  56.4312820" ev="  85.9057549" ra="  97.4534162" dec=" +37.0517480"></ua2_fdata2>
<ua2_fdata2 fno=" 66" b=" 44" bm="000" Lsum="  1219.1" mag="+4.61" az="  63.6679032" ev="  85.9730101" ra="  97.6739563" dec=" +36.5663884"></ua2_fdata2>
<ua2_fdata2 fno=" 67" b=" 41" bm="000" Lsum="   907.1" mag="+4.93" az="  61.1752059" ev="  85.9558081" ra="  97.6008091" dec=" +36.7325850"></ua2_fdata2>
<ua2_fdata2 fno=" 68" b=" 39" bm="000" Lsum="   682.4" mag="+5.24" az="  68.5281406" ev="  85.9707480" ra="  97.8307095" dec=" +36.2492408"></ua2_fdata2>
<ua2_fdata2 fno=" 69" b=" 44" bm="000" Lsum="  1061.4" mag="+4.76" az="  65.9125626" ev="  85.9754175" ra="  97.7466515" dec=" +36.4200294"></ua2_fdata2>
<ua2_fdata2 fno=" 70" b=" 38" bm="000" Lsum="   329.8" mag="+6.03" az="  73.8466777" ev="  85.9462138" ra="  97.9887303" dec=" +35.8961156"></ua2_fdata2>
<ua2_fdata2 fno=" 71" b=" 39" bm="000" Lsum="   457.6" mag="+5.68" az="  71.1779419" ev="  85.9684149" ra="  97.9028224" dec=" +36.0723327"></ua2_fdata2>
<ua2_fdata2 fno=" 72" b=" 41" bm="000" Lsum="   931.4" mag="+4.90" az="  79.4446815" ev="  85.8783267" ra="  98.1611823" dec=" +35.5165093"></ua2_fdata2>
<ua2_fdata2 fno=" 73" b=" 41" bm="000" Lsum="   697.6" mag="+5.22" az="  76.8223428" ev="  85.9155149" ra="  98.0795694" dec=" +35.6958935"></ua2_fdata2>
<ua2_fdata2 fno=" 74" b=" 40" bm="000" Lsum="   391.5" mag="+5.85" az="  84.0868024" ev="  85.7860539" ra="  98.3126430" dec=" +35.1893957"></ua2_fdata2>
<ua2_fdata2 fno=" 75" b=" 44" bm="000" Lsum="   785.4" mag="+5.09" az="  81.7511456" ev="  85.8373791" ra="  98.2345539" dec=" +35.3557186"></ua2_fdata2>
<ua2_fdata2 fno=" 76" b=" 38" bm="000" Lsum="   230.6" mag="+6.42" az="  88.3016176" ev="  85.6770738" ra="  98.4516490" dec=" +34.8775095"></ua2_fdata2>
<ua2_fdata2 fno=" 77" b=" 36" bm="000" Lsum="   296.3" mag="+6.15" az="  86.7678553" ev="  85.7210047" ra="  98.3991984" dec=" +34.9928814"></ua2_fdata2>
	</ua2_objpath>
</ua2_object>
	</ua2_objects>
</ufoanalyzer_record>
